{
	"hero" : {
		"attack" : 6,
		"defense" : 6,
		"knowledge" : 5,
		"mana" : 21,
		"power" : 4,
		"secSkills" : [
			{
				"id" : 6,
				"level" : 3
			},
			{
				"id" : 1,
				"level" : 3
			},
			{
				"id" : 23,
				"level" : 3
			},
			{
				"id" : 15,
				"level" : 2
			}
		],
		"spells" : [
			{
				"canBeCasted" : false,
				"cost" : 4,
				"id" : 15,
				"level" : 2
			},
			{
				"canBeCasted" : true,
				"cost" : 5,
				"id" : 27,
				"level" : 0
			},
			{
				"canBeCasted" : false,
				"cost" : 5,
				"id" : 35,
				"level" : 0
			},
			{
				"canBeCasted" : true,
				"cost" : 5,
				"id" : 41,
				"level" : 0
			},
			{
				"canBeCasted" : true,
				"cost" : 5,
				"id" : 46,
				"level" : 0
			}
		]
	},
	"manaCost" : 0,
	"quickBattle" : false,
	"stacks" : [
		{
			"ability" : [
				{
					"desc" : "Immune to Forgetfulness",
					"type" : 69
				},
				{
					"desc" : "Creature can shoot",
					"type" : 44
				},
				{
					"desc" : "Attacks twice",
					"type" : 46
				}
			],
			"aiValue" : 184,
			"attack" : 12,
			"baseAmount" : 49,
			"defense" : 9,
			"fightValue" : 115,
			"health" : 10,
			"isHuman" : true,
			"isWide" : false,
			"killed" : 1,
			"maxDamage" : 3,
			"minDamage" : 2,
			"name" : "Marksman",
			"slot" : 0,
			"speed" : 6
		},
		{
			"ability" : [
				{
					"desc" : "Creature can shoot",
					"type" : 44
				}
			],
			"aiValue" : 66,
			"attack" : 4,
			"baseAmount" : 13,
			"defense" : 4,
			"fightValue" : 55,
			"health" : 4,
			"isHuman" : false,
			"isWide" : false,
			"killed" : 13,
			"maxDamage" : 2,
			"minDamage" : 1,
			"name" : "Master Gremlin",
			"slot" : 0,
			"speed" : 5
		},
		{
			"ability" : [
				{
					"desc" : "Immune to Forgetfulness",
					"type" : 69
				}
			],
			"aiValue" : 445,
			"attack" : 16,
			"baseAmount" : 12,
			"defense" : 21,
			"fightValue" : 445,
			"health" : 35,
			"isHuman" : true,
			"isWide" : false,
			"killed" : 0,
			"maxDamage" : 9,
			"minDamage" : 6,
			"name" : "Swordsman",
			"slot" : 1,
			"speed" : 5
		},
		{
			"ability" : [
				{
					"desc" : "Creature can shoot",
					"type" : 44
				}
			],
			"aiValue" : 66,
			"attack" : 4,
			"baseAmount" : 13,
			"defense" : 4,
			"fightValue" : 55,
			"health" : 4,
			"isHuman" : false,
			"isWide" : false,
			"killed" : 13,
			"maxDamage" : 2,
			"minDamage" : 1,
			"name" : "Master Gremlin",
			"slot" : 1,
			"speed" : 5
		},
		{
			"ability" : [
				{
					"desc" : "Immune to Forgetfulness",
					"type" : 69
				},
				{
					"desc" : "Can Fly (ignores obstacles)",
					"type" : 43
				},
				{
					"desc" : "Vulnerable to adv. SLAYER",
					"type" : 52
				},
				{
					"desc" : "Does 50% more damage",
					"type" : 50
				},
				{
					"desc" : "Does 50% more damage",
					"type" : 50
				}
			],
			"aiValue" : 5019,
			"attack" : 26,
			"baseAmount" : 3,
			"defense" : 26,
			"fightValue" : 3585,
			"health" : 200,
			"isHuman" : true,
			"isWide" : false,
			"killed" : 0,
			"maxDamage" : 50,
			"minDamage" : 50,
			"name" : "Angel",
			"slot" : 2,
			"speed" : 12
		},
		{
			"ability" : [
				{
					"desc" : "Creature can shoot",
					"type" : 44
				}
			],
			"aiValue" : 66,
			"attack" : 4,
			"baseAmount" : 12,
			"defense" : 4,
			"fightValue" : 55,
			"health" : 4,
			"isHuman" : false,
			"isWide" : false,
			"killed" : 12,
			"maxDamage" : 2,
			"minDamage" : 1,
			"name" : "Master Gremlin",
			"slot" : 2,
			"speed" : 5
		},
		{
			"ability" : [
				{
					"desc" : "Immune to Forgetfulness",
					"type" : 69
				},
				{
					"desc" : "Immune to Champion charge",
					"type" : 45
				}
			],
			"aiValue" : 80,
			"attack" : 10,
			"baseAmount" : 1,
			"defense" : 13,
			"fightValue" : 100,
			"health" : 10,
			"isHuman" : true,
			"isWide" : false,
			"killed" : 0,
			"maxDamage" : 3,
			"minDamage" : 1,
			"name" : "Pikeman",
			"slot" : 3,
			"speed" : 4
		},
		{
			"ability" : [
				{
					"desc" : "Immune to Forgetfulness",
					"type" : 69
				},
				{
					"desc" : "Immune to Champion charge",
					"type" : 45
				}
			],
			"aiValue" : 80,
			"attack" : 10,
			"baseAmount" : 1,
			"defense" : 13,
			"fightValue" : 100,
			"health" : 10,
			"isHuman" : true,
			"isWide" : false,
			"killed" : 0,
			"maxDamage" : 3,
			"minDamage" : 1,
			"name" : "Pikeman",
			"slot" : 4,
			"speed" : 4
		},
		{
			"ability" : [
				{
					"desc" : "Immune to Forgetfulness",
					"type" : 69
				}
			],
			"aiValue" : 100,
			"attack" : 11,
			"baseAmount" : 1,
			"defense" : 10,
			"fightValue" : 100,
			"health" : 8,
			"isHuman" : true,
			"isWide" : true,
			"killed" : 0,
			"maxDamage" : 3,
			"minDamage" : 2,
			"name" : "Centaur",
			"slot" : 5,
			"speed" : 6
		},
		{
			"ability" : [
				{
					"desc" : "Immune to Forgetfulness",
					"type" : 69
				}
			],
			"aiValue" : 100,
			"attack" : 11,
			"baseAmount" : 1,
			"defense" : 10,
			"fightValue" : 100,
			"health" : 8,
			"isHuman" : true,
			"isWide" : true,
			"killed" : 0,
			"maxDamage" : 3,
			"minDamage" : 2,
			"name" : "Centaur",
			"slot" : 6,
			"speed" : 6
		}
	],
	"win" : true
}
