{
	"action" : {
		"actionType" : 7,
		"x" : 6,
		"y" : 4
	},
	"activeStack" : {
		"amount" : 10,
		"amountBase" : 10,
		"attack" : 9,
		"defense" : 6,
		"firstHPleft" : 10,
		"health" : 10,
		"isCanMove" : true,
		"isCanShoot" : true,
		"isHuman" : true,
		"isMoved" : false,
		"isRetaliate" : true,
		"isWaited" : false,
		"isWide" : false,
		"maxDamage" : 3,
		"minDamage" : 2,
		"name" : "Marksman",
		"speed" : 7,
		"x" : 1,
		"y" : 2
	},
	"hero" : {
		"attack" : 2,
		"casted" : false,
		"defense" : 2,
		"knowledge" : 1,
		"mana" : 10,
		"power" : 1,
		"secSkills" : [
			{
				"id" : 6,
				"level" : 1
			},
			{
				"id" : 1,
				"level" : 1
			}
		]
	},
	"obstacles" : [
		{
			"type" : 0,
			"x" : 4,
			"y" : 7
		},
		{
			"type" : 0,
			"x" : 5,
			"y" : 7
		},
		{
			"type" : 0,
			"x" : 9,
			"y" : 5
		},
		{
			"type" : 0,
			"x" : 10,
			"y" : 5
		},
		{
			"type" : 0,
			"x" : 7,
			"y" : 5
		},
		{
			"type" : 0,
			"x" : 7,
			"y" : 3
		},
		{
			"type" : 0,
			"x" : 8,
			"y" : 3
		},
		{
			"type" : 0,
			"x" : 9,
			"y" : 3
		},
		{
			"type" : 0,
			"x" : 10,
			"y" : 3
		},
		{
			"type" : 0,
			"x" : 9,
			"y" : 2
		},
		{
			"type" : 0,
			"x" : 8,
			"y" : 2
		},
		{
			"type" : 0,
			"x" : 7,
			"y" : 2
		},
		{
			"type" : 0,
			"x" : 6,
			"y" : 2
		}
	],
	"stacks" : [
		{
			"amount" : 10,
			"amountBase" : 10,
			"attack" : 9,
			"defense" : 6,
			"firstHPleft" : 10,
			"health" : 10,
			"isCanMove" : true,
			"isCanShoot" : true,
			"isHuman" : true,
			"isMoved" : false,
			"isRetaliate" : true,
			"isWaited" : false,
			"isWide" : false,
			"maxDamage" : 3,
			"minDamage" : 2,
			"name" : "Marksman",
			"speed" : 7,
			"x" : 1,
			"y" : 2
		},
		{
			"amount" : 0,
			"amountBase" : 9,
			"attack" : 4,
			"defense" : 6,
			"firstHPleft" : 2,
			"health" : 6,
			"isCanMove" : false,
			"isCanShoot" : false,
			"isHuman" : false,
			"isMoved" : false,
			"isRetaliate" : false,
			"isWaited" : false,
			"isWide" : false,
			"maxDamage" : 3,
			"minDamage" : 2,
			"name" : "Gnoll Marauder",
			"speed" : 5,
			"x" : 11,
			"y" : 1
		},
		{
			"amount" : 18,
			"amountBase" : 18,
			"attack" : 7,
			"defense" : 9,
			"firstHPleft" : 10,
			"health" : 10,
			"isCanMove" : true,
			"isCanShoot" : false,
			"isHuman" : true,
			"isMoved" : false,
			"isRetaliate" : true,
			"isWaited" : false,
			"isWide" : false,
			"maxDamage" : 3,
			"minDamage" : 1,
			"name" : "Pikeman",
			"speed" : 5,
			"x" : 2,
			"y" : 2
		},
		{
			"amount" : 0,
			"amountBase" : 8,
			"attack" : 4,
			"defense" : 6,
			"firstHPleft" : 1,
			"health" : 6,
			"isCanMove" : false,
			"isCanShoot" : false,
			"isHuman" : false,
			"isMoved" : false,
			"isRetaliate" : false,
			"isWaited" : false,
			"isWide" : false,
			"maxDamage" : 3,
			"minDamage" : 2,
			"name" : "Gnoll Marauder",
			"speed" : 5,
			"x" : 10,
			"y" : 4
		},
		{
			"amount" : 8,
			"amountBase" : 8,
			"attack" : 4,
			"defense" : 6,
			"firstHPleft" : 6,
			"health" : 6,
			"isCanMove" : true,
			"isCanShoot" : false,
			"isHuman" : false,
			"isMoved" : false,
			"isRetaliate" : true,
			"isWaited" : false,
			"isWide" : false,
			"maxDamage" : 3,
			"minDamage" : 2,
			"name" : "Gnoll Marauder",
			"speed" : 5,
			"x" : 6,
			"y" : 4
		},
		{
			"amount" : 1,
			"amountBase" : 1,
			"attack" : 7,
			"defense" : 9,
			"firstHPleft" : 10,
			"health" : 10,
			"isCanMove" : true,
			"isCanShoot" : false,
			"isHuman" : true,
			"isMoved" : false,
			"isRetaliate" : true,
			"isWaited" : false,
			"isWide" : false,
			"maxDamage" : 3,
			"minDamage" : 1,
			"name" : "Pikeman",
			"speed" : 5,
			"x" : 2,
			"y" : 3
		},
		{
			"amount" : 8,
			"amountBase" : 8,
			"attack" : 4,
			"defense" : 6,
			"firstHPleft" : 6,
			"health" : 6,
			"isCanMove" : true,
			"isCanShoot" : false,
			"isHuman" : false,
			"isMoved" : false,
			"isRetaliate" : true,
			"isWaited" : false,
			"isWide" : false,
			"maxDamage" : 3,
			"minDamage" : 2,
			"name" : "Gnoll Marauder",
			"speed" : 5,
			"x" : 7,
			"y" : 6
		}
	]
}
